{"docs":{"0":{"id":0,"title":"BIM","url":"/blog/BIM.html","date":null,"categories":null,"tags":null,"is_post":false},"1":{"id":1,"title":"記事一覧","url":"/blog/","date":null,"categories":null,"tags":null,"is_post":false},"2":{"id":2,"title":"建設プロジェクト効率化のためのクラウドサービスの開発・運営","url":"/","date":null,"categories":null,"tags":null,"is_post":false},"3":{"id":3,"title":"BIMデータの再利用と民主化―― Seeable 社長 Nick Blenkarn との対談","url":"/bim/2019/09/05/BIM%E3%83%87%E3%83%BC%E3%82%BF%E3%81%AE%E5%86%8D%E5%88%A9%E7%94%A8%E3%81%A8%E6%B0%91%E4%B8%BB%E5%8C%96.html","date":"2019-09-05 00:00:00 +0900","categories":["BIM"],"tags":["VR","AR"],"is_post":true},"4":{"id":4,"title":"BIMデータの再利用と民主化―― Seeable 社長 Nick Blenkarn との対談","url":"/bim/2019/09/05/BIM%E3%83%87%E3%83%BC%E3%82%BF%E3%81%AE%E5%86%8D%E5%88%A9%E7%94%A8%E3%81%A8%E6%B0%91%E4%B8%BB%E5%8C%96.html","date":"2019-09-05 00:00:00 +0900","categories":["BIM"],"tags":["VR","AR"],"is_post":true},"5":{"id":5,"title":"BIMデータの再利用と民主化―― Seeable 社長 Nick Blenkarn との対談","url":"/bim/2019/09/05/BIM%E3%83%87%E3%83%BC%E3%82%BF%E3%81%AE%E5%86%8D%E5%88%A9%E7%94%A8%E3%81%A8%E6%B0%91%E4%B8%BB%E5%8C%96.html","date":"2019-09-05 00:00:00 +0900","categories":["BIM"],"tags":["VR","AR"],"is_post":true}},"index":{"version":"0.7.2","fields":[{"name":"title","boost":10},{"name":"categories","boost":20},{"name":"tags","boost":20},{"name":"body","boost":1}],"ref":"id","tokenizer":"default","documentStore":{"store":{"0":["bim","blenkarn","nick","seeabl"],"1":[],"2":["227番地6","300","7月26","zumen"],"3":["100","150","30,000","360","380","3d","5","93","ar","bim","blenkarn","nick","seeabl","vr","vr/ar","zumen"],"4":["100","150","30,000","360","380","3d","5","93","ar","bim","blenkarn","nick","seeabl","vr","vr/ar","zumen"],"5":["100","150","30,000","360","380","3d","5","93","ar","bim","blenkarn","nick","seeabl","vr","vr/ar","zumen"]},"length":6},"tokenStore":{"root":{"1":{"0":{"0":{"docs":{"3":{"ref":3,"tf":0.04878048780487805},"4":{"ref":4,"tf":0.04878048780487805},"5":{"ref":5,"tf":0.04878048780487805}}},"docs":{}},"5":{"0":{"docs":{"3":{"ref":3,"tf":0.024390243902439025},"4":{"ref":4,"tf":0.024390243902439025},"5":{"ref":5,"tf":0.024390243902439025}}},"docs":{}},"docs":{"3":{"ref":3,"tf":0.10416666666666667},"4":{"ref":4,"tf":0.10416666666666667}}},"2":{"2":{"7":{"docs":{},"番":{"docs":{},"地":{"6":{"docs":{"2":{"ref":2,"tf":0.2}}},"docs":{}}}},"docs":{}},"docs":{"3":{"ref":3,"tf":10.0625},"4":{"ref":4,"tf":10.0625}}},"3":{"0":{"0":{"docs":{"2":{"ref":2,"tf":0.2}}},"docs":{},",":{"0":{"0":{"0":{"docs":{"3":{"ref":3,"tf":0.024390243902439025},"4":{"ref":4,"tf":0.024390243902439025},"5":{"ref":5,"tf":0.024390243902439025}}},"docs":{}},"docs":{}},"docs":{}}},"6":{"0":{"docs":{"3":{"ref":3,"tf":0.024390243902439025},"4":{"ref":4,"tf":0.024390243902439025},"5":{"ref":5,"tf":0.024390243902439025}}},"docs":{}},"8":{"0":{"docs":{"3":{"ref":3,"tf":0.024390243902439025},"4":{"ref":4,"tf":0.024390243902439025},"5":{"ref":5,"tf":0.024390243902439025}}},"docs":{}},"docs":{"3":{"ref":3,"tf":0.041666666666666664},"4":{"ref":4,"tf":0.041666666666666664}},"d":{"docs":{"3":{"ref":3,"tf":0.17073170731707318},"4":{"ref":4,"tf":0.17073170731707318},"5":{"ref":5,"tf":0.17073170731707318}}}},"5":{"docs":{"3":{"ref":3,"tf":0.04878048780487805},"4":{"ref":4,"tf":0.04878048780487805},"5":{"ref":5,"tf":0.04878048780487805}}},"7":{"docs":{},"月":{"2":{"6":{"docs":{"2":{"ref":2,"tf":0.4}}},"docs":{}},"docs":{}}},"9":{"3":{"docs":{"3":{"ref":3,"tf":0.04878048780487805},"4":{"ref":4,"tf":0.04878048780487805},"5":{"ref":5,"tf":0.04878048780487805}}},"docs":{}},"docs":{},"b":{"docs":{},"i":{"docs":{},"m":{"docs":{"0":{"ref":0,"tf":10.4},"3":{"ref":3,"tf":22.646341463414632},"4":{"ref":4,"tf":22.646341463414632},"5":{"ref":5,"tf":22.646341463414632}}}},"l":{"docs":{},"e":{"docs":{},"n":{"docs":{},"k":{"docs":{},"a":{"docs":{},"r":{"docs":{},"n":{"docs":{"0":{"ref":0,"tf":0.2},"3":{"ref":3,"tf":2.524390243902439},"4":{"ref":4,"tf":2.524390243902439},"5":{"ref":5,"tf":2.524390243902439}}}}}}}}},"e":{"docs":{},"v":{"docs":{"3":{"ref":3,"tf":0.020833333333333332},"4":{"ref":4,"tf":0.020833333333333332}}}}},"n":{"docs":{},"i":{"docs":{},"c":{"docs":{},"k":{"docs":{"0":{"ref":0,"tf":0.2},"3":{"ref":3,"tf":2.6463414634146343},"4":{"ref":4,"tf":2.6463414634146343},"5":{"ref":5,"tf":2.6463414634146343}}}}}},"s":{"docs":{},"e":{"docs":{},"e":{"docs":{},"a":{"docs":{},"b":{"docs":{},"l":{"docs":{"0":{"ref":0,"tf":0.2},"3":{"ref":3,"tf":2.597560975609756},"4":{"ref":4,"tf":2.597560975609756},"5":{"ref":5,"tf":2.597560975609756}}}}}}},"a":{"docs":{},"m":{"docs":{},"p":{"docs":{},"l":{"docs":{"3":{"ref":3,"tf":0.020833333333333332},"4":{"ref":4,"tf":0.020833333333333332}}}}}}},"z":{"docs":{},"u":{"docs":{},"m":{"docs":{},"e":{"docs":{},"n":{"docs":{"2":{"ref":2,"tf":0.2},"3":{"ref":3,"tf":0.024390243902439025},"4":{"ref":4,"tf":0.024390243902439025},"5":{"ref":5,"tf":0.024390243902439025}}}}}}},"a":{"docs":{},"b":{"docs":{},"c":{"0":{"9":{"8":{"7":{"6":{"docs":{"3":{"ref":3,"tf":0.125},"4":{"ref":4,"tf":0.125}}},"docs":{}},"docs":{}},"docs":{}},"docs":{}},"docs":{}}},"j":{"docs":{},"a":{"docs":{},"x":{"docs":{"3":{"ref":3,"tf":0.020833333333333332},"4":{"ref":4,"tf":0.020833333333333332}}}}},"l":{"docs":{},"e":{"docs":{},"x":{"docs":{"3":{"ref":3,"tf":0.020833333333333332},"4":{"ref":4,"tf":0.020833333333333332}}}}},"r":{"docs":{"3":{"ref":3,"tf":10.048780487804878},"4":{"ref":4,"tf":10.048780487804878},"5":{"ref":5,"tf":10.048780487804878}},"i":{"docs":{},"z":{"docs":{},"o":{"docs":{},"n":{"docs":{},"a":{"docs":{"3":{"ref":3,"tf":0.020833333333333332},"4":{"ref":4,"tf":0.020833333333333332}}}}}}}}},"c":{"docs":{},"u":{"docs":{},"r":{"docs":{},"v":{"docs":{"3":{"ref":3,"tf":0.020833333333333332},"4":{"ref":4,"tf":0.020833333333333332}}}}}},"d":{"docs":{},"i":{"docs":{},"s":{"docs":{},"k":{"docs":{"3":{"ref":3,"tf":0.020833333333333332},"4":{"ref":4,"tf":0.020833333333333332}}}}}},"e":{"docs":{},"l":{"docs":{},"a":{"docs":{},"t":{"docs":{"3":{"ref":3,"tf":0.020833333333333332},"4":{"ref":4,"tf":0.020833333333333332}}}}}},"f":{"docs":{},"a":{"docs":{},"g":{"docs":{"3":{"ref":3,"tf":0.020833333333333332},"4":{"ref":4,"tf":0.020833333333333332}}},"r":{"docs":{"3":{"ref":3,"tf":0.020833333333333332},"4":{"ref":4,"tf":0.020833333333333332}}}}},"h":{"1":{"docs":{"3":{"ref":3,"tf":0.020833333333333332},"4":{"ref":4,"tf":0.020833333333333332}}},"2":{"docs":{"3":{"ref":3,"tf":0.020833333333333332},"4":{"ref":4,"tf":0.020833333333333332}}},"3":{"docs":{"3":{"ref":3,"tf":0.020833333333333332},"4":{"ref":4,"tf":0.020833333333333332}}},"4":{"docs":{"3":{"ref":3,"tf":0.020833333333333332},"4":{"ref":4,"tf":0.020833333333333332}}},"5":{"docs":{"3":{"ref":3,"tf":0.020833333333333332},"4":{"ref":4,"tf":0.020833333333333332}}},"6":{"docs":{"3":{"ref":3,"tf":0.020833333333333332},"4":{"ref":4,"tf":0.020833333333333332}}},"docs":{},"o":{"docs":{},"g":{"docs":{},"e":{"docs":{"3":{"ref":3,"tf":10},"4":{"ref":4,"tf":10}}}}}},"i":{"docs":{},"d":{"docs":{"3":{"ref":3,"tf":0.020833333333333332},"4":{"ref":4,"tf":0.020833333333333332}}},"m":{"docs":{},"g":{"docs":{"3":{"ref":3,"tf":0.041666666666666664},"4":{"ref":4,"tf":0.041666666666666664}}}},"r":{"docs":{},"a":{"docs":{},"q":{"docs":{"3":{"ref":3,"tf":0.020833333333333332},"4":{"ref":4,"tf":0.020833333333333332}}}}}},"j":{"docs":{},"a":{"docs":{},"r":{"docs":{"3":{"ref":3,"tf":0.020833333333333332},"4":{"ref":4,"tf":0.020833333333333332}}}},"u":{"docs":{},"s":{"docs":{},"t":{"docs":{},"i":{"docs":{},"f":{"docs":{},"i":{"docs":{"3":{"ref":3,"tf":0.020833333333333332},"4":{"ref":4,"tf":0.020833333333333332}}}}}}}}},"m":{"docs":{},"a":{"docs":{},"n":{"docs":{"3":{"ref":3,"tf":0.020833333333333332},"4":{"ref":4,"tf":0.020833333333333332}}}}},"o":{"docs":{},"h":{"docs":{"3":{"ref":3,"tf":0.020833333333333332},"4":{"ref":4,"tf":0.020833333333333332}}},"z":{"docs":{"3":{"ref":3,"tf":0.020833333333333332},"4":{"ref":4,"tf":0.020833333333333332}}}},"p":{"docs":{},"i":{"docs":{},"y":{"docs":{},"o":{"docs":{"3":{"ref":3,"tf":10},"4":{"ref":4,"tf":10}}}}},"u":{"docs":{},"g":{"docs":{"3":{"ref":3,"tf":0.020833333333333332},"4":{"ref":4,"tf":0.020833333333333332}}}}},"r":{"docs":{},"u":{"docs":{},"c":{"docs":{},"k":{"docs":{},"’":{"docs":{"3":{"ref":3,"tf":0.020833333333333332},"4":{"ref":4,"tf":0.020833333333333332}}}}}}},"t":{"docs":{},"e":{"docs":{},"x":{"docs":{},"t":{"docs":{"3":{"ref":3,"tf":0.020833333333333332},"4":{"ref":4,"tf":0.020833333333333332}}}}}},"u":{"docs":{},"p":{"docs":{"3":{"ref":3,"tf":0.020833333333333332},"4":{"ref":4,"tf":0.020833333333333332}}}},"w":{"docs":{},"e":{"docs":{},"t":{"docs":{"3":{"ref":3,"tf":0.020833333333333332},"4":{"ref":4,"tf":0.020833333333333332}}}},"i":{"docs":{},"d":{"docs":{},"t":{"docs":{},"h":{"docs":{"3":{"ref":3,"tf":0.020833333333333332},"4":{"ref":4,"tf":0.020833333333333332}}}}}}},"v":{"docs":{},"r":{"docs":{"3":{"ref":3,"tf":10.024390243902438},"4":{"ref":4,"tf":10.024390243902438},"5":{"ref":5,"tf":10.024390243902438}},"/":{"docs":{},"a":{"docs":{},"r":{"docs":{"3":{"ref":3,"tf":0.07317073170731707},"4":{"ref":4,"tf":0.07317073170731707},"5":{"ref":5,"tf":0.07317073170731707}}}}}}}},"length":477},"corpusTokens":["1","100","150","2","227番地6","3","30,000","300","360","380","3d","5","7月26","93","abc09876","ajax","alex","ar","arizona","bev","bim","blenkarn","curv","disk","elat","fag","far","h1","h2","h3","h4","h5","h6","hoge","id","img","iraq","jar","justifi","man","nick","oh","oz","piyo","pug","ruck’","sampl","seeabl","text","up","vr","vr/ar","wet","width","zumen"],"pipeline":["trimmer","stopWordFilter","stemmer"]}}